{
  "title": "ADDRESS: TOPJUMP",
  "outline": [
    {
      "level": "H3",
      "text": "PARKWAY PIGEON FORGE, TN 37863",
      "page": 1,
      "size": 12.4,
      "bold": false,
      "all_upper": true
    },
    {
      "level": "H3",
      "text": "(NEAR DIXIE STAMPEDE ON THE PARKWAY)",
      "page": 1,
      "size": 9.4,
      "bold": false,
      "all_upper": true
    },
    {
      "level": "H2",
      "text": "----------------",
      "page": 1,
      "size": 26.7,
      "bold": false,
      "all_upper": false
    },
    {
      "level": "H3",
      "text": "CLOSED TOED SHOES ARE REQUIRED FOR CLIMBING PARENTS OR GUARDIANS NOT ATTENDING THE PARTY, PLEASE VISIT TO FILL OUT WAIVER TOPJUMP.COM SO YOUR CHILD CAN ATTEND.",
      "page": 1,
      "size": 7.2,
      "bold": false,
      "all_upper": true
    },
    {
      "level": "H3",
      "text": "WWW.TOPJUMP.COM",
      "page": 1,
      "size": 18.0,
      "bold": false,
      "all_upper": true
    }
  ],
  "source": "file05.pdf"
}